kr/__init__.py
kr/config.py
kr/consoles.py
kr/download.py
kr/search.py
kr_cli-0.1.1.dist-info/LICENSE
kr_cli-0.1.1.dist-info/METADATA
kr_cli-0.1.1.dist-info/WHEEL
kr_cli-0.1.1.dist-info/entry_points.txt
kr_cli-0.1.1.dist-info/top_level.txt
kr_cli-0.1.1.dist-info/RECORD
