Metadata-Version: 2.1
Name: kr-cli
Version: 0.1.1
Summary: CLI tool to search and download roms from Killers Roms
Home-page: https://github.com/jonatasleon/kr-cli
Author: Jonatas Leon
Author-email: j@jonatasleon.com
License: MIT
Platform: UNKNOWN
Classifier: License :: OSI Approved :: MIT License
Classifier: Programming Language :: Python :: 3
Classifier: Programming Language :: Python :: 3.6
Requires-Dist: Click
Requires-Dist: beautifulsoup4
Requires-Dist: requests
Requires-Dist: tabulate
